Metadata-Version: 2.1
Name: odoo-addon-autovacuum_message_attachment
Version: 18.0.1.0.1.26
Requires-Python: >=3.10
Requires-Dist: odoo==18.0.*
Summary: Automatically delete old mail messages and attachments
Home-page: https://github.com/OCA/server-tools
License: LGPL-3
Author: Akretion, Odoo Community Association (OCA)
Author-email: support@odoo-community.org
Classifier: Programming Language :: Python
Classifier: Framework :: Odoo
Classifier: Framework :: Odoo :: 18.0
Classifier: License :: OSI Approved :: GNU Lesser General Public License v3 (LGPLv3)
